viseng/__init__.py
viseng/annotations.py
viseng/figure.py
viseng/function.py
viseng/patches.py
viseng/run.py
viseng/utils.py
viseng-0.1.dist-info/LICENSE.txt
viseng-0.1.dist-info/METADATA
viseng-0.1.dist-info/WHEEL
viseng-0.1.dist-info/top_level.txt
viseng-0.1.dist-info/RECORD
