Metadata-Version: 2.1
Name: viseng
Version: 0.1
Summary: Visualisation library for producing graphics from Python's Matplotlib
Home-page: https://github.com/OllieBoyne/viseng
Author: ollie
Author-email: ollieboyne@gmail.com
License: UNKNOWN
Platform: UNKNOWN
